app/__init__.py
app/api.py
app/commands.py
app/logo.py
app/main.py
app/os_system.py
app/prompts.py
AIConsole_o-0.3.dist-info/LICENSE
AIConsole_o-0.3.dist-info/METADATA
AIConsole_o-0.3.dist-info/WHEEL
AIConsole_o-0.3.dist-info/entry_points.txt
AIConsole_o-0.3.dist-info/top_level.txt
AIConsole_o-0.3.dist-info/RECORD
