Metadata-Version: 2.1
Name: AIConsole-o
Version: 0.3
Summary: An AI-powered assistant for command-line operations, networking configurations, and file system management, and more...
Home-page: https://github.com/houssam-nxy/Aiconsole-o
Author: Houssam El Khesassi
Author-email: elkhesassi@gmail.com
Classifier: Programming Language :: Python :: 3
Classifier: License :: OSI Approved :: MIT License
Classifier: Operating System :: OS Independent
Requires-Python: >=3.6
License-File: LICENSE
Requires-Dist: google-generativeai
Requires-Dist: python-dotenv
Requires-Dist: colorama
